timesage/Period.py
timesage/Time.py
timesage/__init__.py
timesage-0.0.2.dist-info/licenses/LICENSE
timesage-0.0.2.dist-info/METADATA
timesage-0.0.2.dist-info/WHEEL
timesage-0.0.2.dist-info/top_level.txt
timesage-0.0.2.dist-info/RECORD
