Metadata-Version: 2.4
Name: TimeSage
Version: 0.0.2
Summary: A pip package for calculating time.
Author-email: Zeyu Xie <xie.zeyu20@gmail.com>
License: GPL-3.0-only
Project-URL: Homepage, https://github.com/Zeyu-Xie/Lavender-Timesage
Classifier: Programming Language :: Python :: 3
Classifier: License :: OSI Approved :: GNU General Public License v3 (GPLv3)
Classifier: Operating System :: OS Independent
Requires-Python: >=3.6
License-File: LICENSE
Dynamic: license-file
